.long-description.html
MANIFEST.in
README.txt
distribute-0.6.24.tar.gz
setup.py
collective/__init__.py
collective.contacts.egg-info/PKG-INFO
collective.contacts.egg-info/SOURCES.txt
collective.contacts.egg-info/dependency_links.txt
collective.contacts.egg-info/entry_points.txt
collective.contacts.egg-info/namespace_packages.txt
collective.contacts.egg-info/not-zip-safe
collective.contacts.egg-info/requires.txt
collective.contacts.egg-info/top_level.txt
collective/contacts/README.txt
collective/contacts/__init__.py
collective/contacts/columns.py
collective/contacts/columns.zcml
collective/contacts/config.py
collective/contacts/configure.zcml
collective/contacts/export.py
collective/contacts/export.zcml
collective/contacts/import.py
collective/contacts/import.zcml
collective/contacts/imports.py
collective/contacts/search.py
collective/contacts/search.zcml
collective/contacts/setuphandlers.py
collective/contacts/skins.zcml
collective/contacts/table.py
collective/contacts/table.zcml
collective/contacts/translate.sh
collective/contacts/updates.zcml
collective/contacts/user.csv
collective/contacts/vocabularies.py
collective/contacts/vocabularies.zcml
collective/contacts/Extensions/Install.py
collective/contacts/Extensions/__init__.py
collective/contacts/browser/__init__.py
collective/contacts/browser/actions.py
collective/contacts/browser/address_book_view.py
collective/contacts/browser/configure.zcml
collective/contacts/browser/customize.py
collective/contacts/browser/customize.zcml
collective/contacts/browser/export.py
collective/contacts/browser/export.zcml
collective/contacts/browser/find.py
collective/contacts/browser/group.py
collective/contacts/browser/import.py
collective/contacts/browser/import.zcml
collective/contacts/browser/importview.py
collective/contacts/browser/kss.zcml
collective/contacts/browser/ksscommands.py
collective/contacts/browser/list.py
collective/contacts/browser/list.zcml
collective/contacts/browser/organization.py
collective/contacts/browser/search.py
collective/contacts/browser/search.zcml
collective/contacts/browser/resources/Add.gif
collective/contacts/browser/resources/EditIcon.gif
collective/contacts/browser/resources/Remove.gif
collective/contacts/browser/resources/address_book.js
collective/contacts/browser/resources/addressbook.gif
