Metadata-Version: 1.0
Name: collective.contacts
Version: 1.5.2
Summary: Address book product for Plone
Home-page: http://plone.org/products/collective.contacts
Author: Franco Pellegrini
Author-email: frapell@menttes.com
License: GPL
Keywords: plone addressbook collective contacts
Platform: UNKNOWN
Classifier: Framework :: Plone
Classifier: Framework :: Plone :: 3.3
Classifier: Framework :: Plone :: 4.0
Classifier: Framework :: Plone :: 4.1
Classifier: Intended Audience :: Developers
Classifier: Intended Audience :: End Users/Desktop
Classifier: Topic :: Software Development :: Libraries :: Python Modules
Classifier: License :: OSI Approved :: GNU General Public License (GPL)
